MANIFEST.in
README.rst
setup.py
aliyun_python_sdk_oos_test.egg-info/PKG-INFO
aliyun_python_sdk_oos_test.egg-info/SOURCES.txt
aliyun_python_sdk_oos_test.egg-info/dependency_links.txt
aliyun_python_sdk_oos_test.egg-info/requires.txt
aliyun_python_sdk_oos_test.egg-info/top_level.txt
aliyunsdkoos/__init__.py
aliyunsdkoos/request/__init__.py
aliyunsdkoos/request/v20190601/CancelExecutionRequest.py
aliyunsdkoos/request/v20190601/CreateTemplateRequest.py
aliyunsdkoos/request/v20190601/DeleteExecutionsRequest.py
aliyunsdkoos/request/v20190601/DeleteTemplateRequest.py
aliyunsdkoos/request/v20190601/GenerateExecutionPolicyRequest.py
aliyunsdkoos/request/v20190601/GetExecutionTemplateRequest.py
aliyunsdkoos/request/v20190601/GetTemplateRequest.py
aliyunsdkoos/request/v20190601/ListActionsRequest.py
aliyunsdkoos/request/v20190601/ListExecutionLogsRequest.py
aliyunsdkoos/request/v20190601/ListExecutionsRequest.py
aliyunsdkoos/request/v20190601/ListTaskExecutionsRequest.py
aliyunsdkoos/request/v20190601/ListTemplatesRequest.py
aliyunsdkoos/request/v20190601/NotifyExecutionRequest.py
aliyunsdkoos/request/v20190601/StartExecutionRequest.py
aliyunsdkoos/request/v20190601/UpdateTemplateRequest.py
aliyunsdkoos/request/v20190601/ValidateTemplateContentRequest.py
aliyunsdkoos/request/v20190601/__init__.py